statictemplate/models.py
statictemplate/settings.py
statictemplate/tests.py
statictemplate/__init__.py
statictemplate/management/__init__.py
statictemplate/management/commands/__init__.py
statictemplate/management/commands/statictemplate.py
django_statictemplate-2.0.1.dist-info/top_level.txt
django_statictemplate-2.0.1.dist-info/METADATA
django_statictemplate-2.0.1.dist-info/DESCRIPTION.rst
django_statictemplate-2.0.1.dist-info/metadata.json
django_statictemplate-2.0.1.dist-info/WHEEL
django_statictemplate-2.0.1.dist-info/RECORD
