Metadata-Version: 2.0
Name: django-statictemplate
Version: 2.0.1
Summary: This project aims at providing a compromise between dynamic error pages for Django (that use template tags etc and therefore potentially error too) and having to write static error pages by hand.
Home-page: https://github.com/ojii/django-statictemplate
Author: Jonas Obrist
Author-email: ojiidotch@gmail.com
License: LICENSE
Platform: OS Independent
Requires-Dist: django (>=1.2)
